{
  "formatVersion": 1,
  "database": {
    "version": 1,
    "identityHash": "be4cc9b0a8910f6359867b33470efcf4",
    "entities": [
      {
        "tableName": "category",
        "createSql": "CREATE TABLE IF NOT EXISTS `${TABLE_NAME}` (`categoryId` INTEGER PRIMARY KEY AUTOINCREMENT NOT NULL, `passed` INTEGER NOT NULL, `title` TEXT NOT NULL)",
        "fields": [
          {
            "fieldPath": "categoryId",
            "columnName": "categoryId",
            "affinity": "INTEGER",
            "notNull": true
          },
          {
            "fieldPath": "passed",
            "columnName": "passed",
            "affinity": "INTEGER",
            "notNull": true
          },
          {
            "fieldPath": "title",
            "columnName": "title",
            "affinity": "TEXT",
            "notNull": true
          }
        ],
        "primaryKey": {
          "columnNames": [
            "categoryId"
          ],
          "autoGenerate": true
        },
        "indices": [
          {
            "name": "index_category_title",
            "unique": true,
            "columnNames": [
              "title"
            ],
            "createSql": "CREATE UNIQUE INDEX `index_category_title` ON `${TABLE_NAME}` (`title`)"
          }
        ],
        "foreignKeys": []
      },
      {
        "tableName": "level",
        "createSql": "CREATE TABLE IF NOT EXISTS `${TABLE_NAME}` (`levelId` INTEGER PRIMARY KEY AUTOINCREMENT NOT NULL, `levelCategoryId` INTEGER NOT NULL, `passed` INTEGER NOT NULL, `title` TEXT NOT NULL, FOREIGN KEY(`levelCategoryId`) REFERENCES `category`(`categoryId`) ON UPDATE NO ACTION ON DELETE CASCADE )",
        "fields": [
          {
            "fieldPath": "levelId",
            "columnName": "levelId",
            "affinity": "INTEGER",
            "notNull": true
          },
          {
            "fieldPath": "levelCategoryId",
            "columnName": "levelCategoryId",
            "affinity": "INTEGER",
            "notNull": true
          },
          {
            "fieldPath": "passed",
            "columnName": "passed",
            "affinity": "INTEGER",
            "notNull": true
          },
          {
            "fieldPath": "title",
            "columnName": "title",
            "affinity": "TEXT",
            "notNull": true
          }
        ],
        "primaryKey": {
          "columnNames": [
            "levelId"
          ],
          "autoGenerate": true
        },
        "indices": [
          {
            "name": "index_level_title",
            "unique": false,
            "columnNames": [
              "title"
            ],
            "createSql": "CREATE  INDEX `index_level_title` ON `${TABLE_NAME}` (`title`)"
          },
          {
            "name": "index_level_levelCategoryId",
            "unique": false,
            "columnNames": [
              "levelCategoryId"
            ],
            "createSql": "CREATE  INDEX `index_level_levelCategoryId` ON `${TABLE_NAME}` (`levelCategoryId`)"
          }
        ],
        "foreignKeys": [
          {
            "table": "category",
            "onDelete": "CASCADE",
            "onUpdate": "NO ACTION",
            "columns": [
              "levelCategoryId"
            ],
            "referencedColumns": [
              "categoryId"
            ]
          }
        ]
      },
      {
        "tableName": "question",
        "createSql": "CREATE TABLE IF NOT EXISTS `${TABLE_NAME}` (`questionId` INTEGER PRIMARY KEY AUTOINCREMENT NOT NULL, `questionLevelId` INTEGER NOT NULL, `title` TEXT NOT NULL, `question` TEXT NOT NULL, `rightAnswer` TEXT NOT NULL, `passed` INTEGER NOT NULL, FOREIGN KEY(`questionLevelId`) REFERENCES `level`(`levelId`) ON UPDATE NO ACTION ON DELETE CASCADE )",
        "fields": [
          {
            "fieldPath": "questionId",
            "columnName": "questionId",
            "affinity": "INTEGER",
            "notNull": true
          },
          {
            "fieldPath": "questionLevelId",
            "columnName": "questionLevelId",
            "affinity": "INTEGER",
            "notNull": true
          },
          {
            "fieldPath": "title",
            "columnName": "title",
            "affinity": "TEXT",
            "notNull": true
          },
          {
            "fieldPath": "question",
            "columnName": "question",
            "affinity": "TEXT",
            "notNull": true
          },
          {
            "fieldPath": "rightAnswer",
            "columnName": "rightAnswer",
            "affinity": "TEXT",
            "notNull": true
          },
          {
            "fieldPath": "passed",
            "columnName": "passed",
            "affinity": "INTEGER",
            "notNull": true
          }
        ],
        "primaryKey": {
          "columnNames": [
            "questionId"
          ],
          "autoGenerate": true
        },
        "indices": [
          {
            "name": "index_question_title",
            "unique": false,
            "columnNames": [
              "title"
            ],
            "createSql": "CREATE  INDEX `index_question_title` ON `${TABLE_NAME}` (`title`)"
          },
          {
            "name": "index_question_questionLevelId",
            "unique": false,
            "columnNames": [
              "questionLevelId"
            ],
            "createSql": "CREATE  INDEX `index_question_questionLevelId` ON `${TABLE_NAME}` (`questionLevelId`)"
          }
        ],
        "foreignKeys": [
          {
            "table": "level",
            "onDelete": "CASCADE",
            "onUpdate": "NO ACTION",
            "columns": [
              "questionLevelId"
            ],
            "referencedColumns": [
              "levelId"
            ]
          }
        ]
      },
      {
        "tableName": "record",
        "createSql": "CREATE TABLE IF NOT EXISTS `${TABLE_NAME}` (`recordId` INTEGER PRIMARY KEY AUTOINCREMENT NOT NULL, `numberOfQuestions` INTEGER NOT NULL, `time` INTEGER NOT NULL)",
        "fields": [
          {
            "fieldPath": "recordId",
            "columnName": "recordId",
            "affinity": "INTEGER",
            "notNull": true
          },
          {
            "fieldPath": "numberOfQuestions",
            "columnName": "numberOfQuestions",
            "affinity": "INTEGER",
            "notNull": true
          },
          {
            "fieldPath": "time",
            "columnName": "time",
            "affinity": "INTEGER",
            "notNull": true
          }
        ],
        "primaryKey": {
          "columnNames": [
            "recordId"
          ],
          "autoGenerate": true
        },
        "indices": [],
        "foreignKeys": []
      }
    ],
    "setupQueries": [
      "CREATE TABLE IF NOT EXISTS room_master_table (id INTEGER PRIMARY KEY,identity_hash TEXT)",
      "INSERT OR REPLACE INTO room_master_table (id,identity_hash) VALUES(42, \"be4cc9b0a8910f6359867b33470efcf4\")"
    ]
  }
}